{"metadata": {"resultset": {"offset": 1, "count": 274, "limit": 1000}}, "results": [{"date": "2000-01-01T00:00:00", "datatype": "CDSD", "station": "GHCND:USC00241875", "value": 324.9}, {"date": "2000-01-01T00:00:00", "datatype": "CLDD", "station": "GHCND:USC00241875", "attributes": "0", "value": 324.9}, {"date": "2000-01-01T00:00:00", "datatype": "DP01", "station": "GHCND:USC00241875", "attributes": "0", "value": 57}, {"date": "2000-01-01T00:00:00", "datatype": "DP10", "station": "GHCND:USC00241875", "attributes": "0", "value": 32}, {"date": "2000-01-01T00:00:00", "datatype": "DP1X", "station": "GHCND:USC00241875", "attributes": "0", "value": 1}, {"date": "2000-01-01T00:00:00", "datatype": "DSNW", "station": "GHCND:USC00241875", "attributes": "0", "value": 13}, {"date": "2000-01-01T00:00:00", "datatype": "DT00", "station": "GHCND:USC00241875", "attributes": "0", "value": 35}, {"date": "2000-01-01T00:00:00", "datatype": "DT32", "station": "GHCND:USC00241875", "attributes": "0", "value": 175}, {"date": "2000-01-01T00:00:00", "datatype": "DX32", "station": "GHCND:USC00241875", "attributes": "0", "value": 57}, {"date": "2000-01-01T00:00:00", "datatype": "DX70", "station": "GHCND:USC00241875", "attributes": "0", "value": 133}, {"date": "2000-01-01T00:00:00", "datatype": "DX90", "station": "GHCND:USC00241875", "attributes": "0", "value": 36}, {"date": "2000-01-01T00:00:00", "datatype": "DYFG", "station": "GHCND:USC00241875", "attributes": " ", "value": 13}, {"date": "2000-01-01T00:00:00", "datatype": "DYTS", "station": "GHCND:USC00241875", "attributes": " ", "value": 12}, {"date": "2000-01-01T00:00:00", "datatype": "EMNT", "station": "GHCND:USC00241875", "attributes": "0,1212, ", "value": -30.6}, {"date": "2000-01-01T00:00:00", "datatype": "EMSN", "station": "GHCND:USC00241875", "attributes": " ,0,1106, ", "value": 114}, {"date": "2000-01-01T00:00:00", "datatype": "EMXP", "station": "GHCND:USC00241875", "attributes": " ,0,0709, ", "value": 29.2}, {"date": "2000-01-01T00:00:00", "datatype": "EMXT", "station": "GHCND:USC00241875", "attributes": "0,0810, ", "value": 40}, {"date": "2000-01-01T00:00:00", "datatype": "FZF0", "station": "GHCND:USC00241875", "attributes": "0,0922", "value": -1.7}, {"date": "2000-01-01T00:00:00", "datatype": "FZF1", "station": "GHCND:USC00241875", "attributes": "0,0924", "value": -2.2}, {"date": "2000-01-01T00:00:00", "datatype": "FZF2", "station": "GHCND:USC00241875", "attributes": "0,1005", "value": -7.8}, {"date": "2000-01-01T00:00:00", "datatype": "FZF3", "station": "GHCND:USC00241875", "attributes": "0,1005", "value": -7.8}, {"date": "2000-01-01T00:00:00", "datatype": "FZF4", "station": "GHCND:USC00241875", "attributes": "0,1007", "value": -11.7}, {"date": "2000-01-01T00:00:00", "datatype": "FZF5", "station": "GHCND:USC00241875", "attributes": "0,0602", "value": -0.6}, {"date": "2000-01-01T00:00:00", "datatype": "FZF6", "station": "GHCND:USC00241875", "attributes": "0,0514", "value": -3.9}, {"date": "2000-01-01T00:00:00", "datatype": "FZF7", "station": "GHCND:USC00241875", "attributes": "0,0416", "value": -6.1}, {"date": "2000-01-01T00:00:00", "datatype": "FZF8", "station": "GHCND:USC00241875", "attributes": "0,0415", "value": -6.7}, {"date": "2000-01-01T00:00:00", "datatype": "FZF9", "station": "GHCND:USC00241875", "attributes": "0,0325", "value": -10}, {"date": "2000-01-01T00:00:00", "datatype": "HDSD", "station": "GHCND:USC00241875", "attributes": "4", "value": 3608.4}, {"date": "2000-01-01T00:00:00", "datatype": "HTDD", "station": "GHCND:USC00241875", "attributes": "0", "value": 3608.4}, {"date": "2000-01-01T00:00:00", "datatype": "PRCP", "station": "GHCND:USC00241875", "attributes": " ,0", "value": 285.8}, {"date": "2000-01-01T00:00:00", "datatype": "SNOW", "station": "GHCND:USC00241875", "attributes": " ,0", "value": 729}, {"date": "2000-01-01T00:00:00", "datatype": "TAVG", "station": "GHCND:USC00241875", "attributes": "0", "value": 7}, {"date": "2000-01-01T00:00:00", "datatype": "TMAX", "station": "GHCND:USC00241875", "attributes": "0", "value": 14.75}, {"date": "2000-01-01T00:00:00", "datatype": "TMIN", "station": "GHCND:USC00241875", "attributes": "0", "value": -0.75}, {"date": "2001-01-01T00:00:00", "datatype": "CDSD", "station": "GHCND:USC00241875", "value": 371.5}, {"date": "2001-01-01T00:00:00", "datatype": "CLDD", "station": "GHCND:USC00241875", "attributes": "0", "value": 371.5}, {"date": "2001-01-01T00:00:00", "datatype": "DP01", "station": "GHCND:USC00241875", "attributes": "0", "value": 56}, {"date": "2001-01-01T00:00:00", "datatype": "DP10", "station": "GHCND:USC00241875", "attributes": "0", "value": 25}, {"date": "2001-01-01T00:00:00", "datatype": "DP1X", "station": "GHCND:USC00241875", "attributes": "0", "value": 1}, {"date": "2001-01-01T00:00:00", "datatype": "DSNW", "station": "GHCND:USC00241875", "attributes": "0", "value": 0}, {"date": "2001-01-01T00:00:00", "datatype": "DT00", "station": "GHCND:USC00241875", "attributes": "0", "value": 14}, {"date": "2001-01-01T00:00:00", "datatype": "DT32", "station": "GHCND:USC00241875", "attributes": "0", "value": 171}, {"date": "2001-01-01T00:00:00", "datatype": "DX32", "station": "GHCND:USC00241875", "attributes": "0", "value": 46}, {"date": "2001-01-01T00:00:00", "datatype": "DX70", "station": "GHCND:USC00241875", "attributes": "0", "value": 138}, {"date": "2001-01-01T00:00:00", "datatype": "DX90", "station": "GHCND:USC00241875", "attributes": "0", "value": 39}, {"date": "2001-01-01T00:00:00", "datatype": "DYFG", "station": "GHCND:USC00241875", "attributes": " ", "value": 7}, {"date": "2001-01-01T00:00:00", "datatype": "DYTS", "station": "GHCND:USC00241875", "attributes": " ", "value": 15}, {"date": "2001-01-01T00:00:00", "datatype": "EMNT", "station": "GHCND:USC00241875", "attributes": "0,0226,+", "value": -27.8}, {"date": "2001-01-01T00:00:00", "datatype": "EMSN", "station": "GHCND:USC00241875", "attributes": "T,0,0131,+", "value": 0}, {"date": "2001-01-01T00:00:00", "datatype": "EMXP", "station": "GHCND:USC00241875", "attributes": " ,0,0613, ", "value": 25.7}, {"date": "2001-01-01T00:00:00", "datatype": "EMXT", "station": "GHCND:USC00241875", "attributes": "0,0803, ", "value": 40}, {"date": "2001-01-01T00:00:00", "datatype": "FZF0", "station": "GHCND:USC00241875", "attributes": "0,1003", "value": 0}, {"date": "2001-01-01T00:00:00", "datatype": "FZF1", "station": "GHCND:USC00241875", "attributes": "0,1005", "value": -6.7}, {"date": "2001-01-01T00:00:00", "datatype": "FZF2", "station": "GHCND:USC00241875", "attributes": "0,1005", "value": -6.7}, {"date": "2001-01-01T00:00:00", "datatype": "FZF3", "station": "GHCND:USC00241875", "attributes": "0,1005", "value": -6.7}, {"date": "2001-01-01T00:00:00", "datatype": "FZF4", "station": "GHCND:USC00241875", "attributes": "0,1108", "value": -9.4}, {"date": "2001-01-01T00:00:00", "datatype": "FZF5", "station": "GHCND:USC00241875", "attributes": "0,0524", "value": 0}, {"date": "2001-01-01T00:00:00", "datatype": "FZF6", "station": "GHCND:USC00241875", "attributes": "0,0503", "value": -3.3}, {"date": "2001-01-01T00:00:00", "datatype": "FZF7", "station": "GHCND:USC00241875", "attributes": "0,0422", "value": -5.6}, {"date": "2001-01-01T00:00:00", "datatype": "FZF8", "station": "GHCND:USC00241875", "attributes": "0,0416", "value": -11.1}, {"date": "2001-01-01T00:00:00", "datatype": "FZF9", "station": "GHCND:USC00241875", "attributes": "0,0416", "value": -11.1}, {"date": "2001-01-01T00:00:00", "datatype": "HDSD", "station": "GHCND:USC00241875", "attributes": "9", "value": 4384.9}, {"date": "2001-01-01T00:00:00", "datatype": "HTDD", "station": "GHCND:USC00241875", "attributes": "0", "value": 4384.9}, {"date": "2001-01-01T00:00:00", "datatype": "PRCP", "station": "GHCND:USC00241875", "attributes": " ,0", "value": 248.1}, {"date": "2001-01-01T00:00:00", "datatype": "SNOW", "station": "GHCND:USC00241875", "attributes": "T,0", "value": 0}, {"date": "2001-01-01T00:00:00", "datatype": "TAVG", "station": "GHCND:USC00241875", "attributes": "0", "value": 8.23}, {"date": "2001-01-01T00:00:00", "datatype": "TMAX", "station": "GHCND:USC00241875", "attributes": "0", "value": 15.73}, {"date": "2001-01-01T00:00:00", "datatype": "TMIN", "station": "GHCND:USC00241875", "attributes": "0", "value": 0.72}, {"date": "2002-01-01T00:00:00", "datatype": "CDSD", "station": "GHCND:USC00241875", "value": 304.4}, {"date": "2002-01-01T00:00:00", "datatype": "CLDD", "station": "GHCND:USC00241875", "attributes": "0", "value": 304.4}, {"date": "2002-01-01T00:00:00", "datatype": "DP01", "station": "GHCND:USC00241875", "attributes": "0", "value": 54}, {"date": "2002-01-01T00:00:00", "datatype": "DP10", "station": "GHCND:USC00241875", "attributes": "0", "value": 29}, {"date": "2002-01-01T00:00:00", "datatype": "DP1X", "station": "GHCND:USC00241875", "attributes": "0", "value": 1}, {"date": "2002-01-01T00:00:00", "datatype": "DSND", "station": "GHCND:USC00241875", "value": 30}, {"date": "2002-01-01T00:00:00", "datatype": "DT00", "station": "GHCND:USC00241875", "attributes": "0", "value": 30}, {"date": "2002-01-01T00:00:00", "datatype": "DT32", "station": "GHCND:USC00241875", "attributes": "0", "value": 191}, {"date": "2002-01-01T00:00:00", "datatype": "DX32", "station": "GHCND:USC00241875", "attributes": "0", "value": 45}, {"date": "2002-01-01T00:00:00", "datatype": "DX70", "station": "GHCND:USC00241875", "attributes": "0", "value": 118}, {"date": "2002-01-01T00:00:00", "datatype": "DX90", "station": "GHCND:USC00241875", "attributes": "0", "value": 27}, {"date": "2002-01-01T00:00:00", "datatype": "DYTS", "station": "GHCND:USC00241875", "attributes": " ", "value": 7}, {"date": "2002-01-01T00:00:00", "datatype": "EMNT", "station": "GHCND:USC00241875", "attributes": "0,0309, ", "value": -32.8}, {"date": "2002-01-01T00:00:00", "datatype": "EMSD", "station": "GHCND:USC00241875", "attributes": " ,0,0322,+", "value": 229}, {"date": "2002-01-01T00:00:00", "datatype": "EMXP", "station": "GHCND:USC00241875", "attributes": " ,0,0717, ", "value": 27.9}, {"date": "2002-01-01T00:00:00", "datatype": "EMXT", "station": "GHCND:USC00241875", "attributes": "0,0714, ", "value": 43.3}, {"date": "2002-01-01T00:00:00", "datatype": "FZF0", "station": "GHCND:USC00241875", "attributes": "0,0922", "value": -2.2}, {"date": "2002-01-01T00:00:00", "datatype": "FZF1", "station": "GHCND:USC00241875", "attributes": "0,0922", "value": -2.2}, {"date": "2002-01-01T00:00:00", "datatype": "FZF2", "station": "GHCND:USC00241875", "attributes": "0,1012", "value": -5}, {"date": "2002-01-01T00:00:00", "datatype": "FZF3", "station": "GHCND:USC00241875", "attributes": "0,1022", "value": -13.9}, {"date": "2002-01-01T00:00:00", "datatype": "FZF4", "station": "GHCND:USC00241875", "attributes": "0,1022", "value": -13.9}, {"date": "2002-01-01T00:00:00", "datatype": "FZF5", "station": "GHCND:USC00241875", "attributes": "0,0524", "value": -2.2}, {"date": "2002-01-01T00:00:00", "datatype": "FZF6", "station": "GHCND:USC00241875", "attributes": "0,0524", "value": -2.2}, {"date": "2002-01-01T00:00:00", "datatype": "FZF7", "station": "GHCND:USC00241875", "attributes": "0,0517", "value": -5}, {"date": "2002-01-01T00:00:00", "datatype": "FZF8", "station": "GHCND:USC00241875", "attributes": "0,0504", "value": -8.3}, {"date": "2002-01-01T00:00:00", "datatype": "FZF9", "station": "GHCND:USC00241875", "attributes": "0,0404", "value": -9.4}, {"date": "2002-01-01T00:00:00", "datatype": "HDSD", "station": "GHCND:USC00241875", "attributes": "0", "value": 4240}, {"date": "2002-01-01T00:00:00", "datatype": "HTDD", "station": "GHCND:USC00241875", "attributes": "0", "value": 4240}, {"date": "2002-01-01T00:00:00", "datatype": "PRCP", "station": "GHCND:USC00241875", "attributes": " ,0", "value": 255.5}, {"date": "2002-01-01T00:00:00", "datatype": "TAVG", "station": "GHCND:USC00241875", "attributes": "0", "value": 6.8}, {"date": "2002-01-01T00:00:00", "datatype": "TMAX", "station": "GHCND:USC00241875", "attributes": "0", "value": 14.44}, {"date": "2002-01-01T00:00:00", "datatype": "TMIN", "station": "GHCND:USC00241875", "attributes": "0", "value": -0.83}, {"date": "2003-01-01T00:00:00", "datatype": "DP01", "station": "GHCND:USC00241875", "attributes": "0", "value": 72}, {"date": "2003-01-01T00:00:00", "datatype": "DP10", "station": "GHCND:USC00241875", "attributes": "0", "value": 39}, {"date": "2003-01-01T00:00:00", "datatype": "DP1X", "station": "GHCND:USC00241875", "attributes": "0", "value": 1}, {"date": "2003-01-01T00:00:00", "datatype": "DYFG", "station": "GHCND:USC00241875", "attributes": " ", "value": 5}, {"date": "2003-01-01T00:00:00", "datatype": "EMXP", "station": "GHCND:USC00241875", "attributes": " ,0,1029, ", "value": 25.9}, {"date": "2003-01-01T00:00:00", "datatype": "HDSD", "station": "GHCND:USC00241875", "attributes": "8", "value": 4173.8}, {"date": "2003-01-01T00:00:00", "datatype": "HTDD", "station": "GHCND:USC00241875", "attributes": "0", "value": 4173.8}, {"date": "2003-01-01T00:00:00", "datatype": "PRCP", "station": "GHCND:USC00241875", "attributes": " ,0", "value": 282.7}, {"date": "2004-01-01T00:00:00", "datatype": "CDSD", "station": "GHCND:USC00241875", "value": 171.6}, {"date": "2004-01-01T00:00:00", "datatype": "CLDD", "station": "GHCND:USC00241875", "attributes": "0", "value": 171.6}, {"date": "2004-01-01T00:00:00", "datatype": "DP01", "station": "GHCND:USC00241875", "attributes": "0", "value": 59}, {"date": "2004-01-01T00:00:00", "datatype": "DP10", "station": "GHCND:USC00241875", "attributes": "0", "value": 31}, {"date": "2004-01-01T00:00:00", "datatype": "DP1X", "station": "GHCND:USC00241875", "attributes": "0", "value": 0}, {"date": "2004-01-01T00:00:00", "datatype": "DT00", "station": "GHCND:USC00241875", "attributes": "0", "value": 23}, {"date": "2004-01-01T00:00:00", "datatype": "DT32", "station": "GHCND:USC00241875", "attributes": "0", "value": 175}, {"date": "2004-01-01T00:00:00", "datatype": "DX32", "station": "GHCND:USC00241875", "attributes": "0", "value": 36}, {"date": "2004-01-01T00:00:00", "datatype": "DX70", "station": "GHCND:USC00241875", "attributes": "0", "value": 131}, {"date": "2004-01-01T00:00:00", "datatype": "DX90", "station": "GHCND:USC00241875", "attributes": "0", "value": 16}, {"date": "2004-01-01T00:00:00", "datatype": "DYFG", "station": "GHCND:USC00241875", "attributes": " ", "value": 6}, {"date": "2004-01-01T00:00:00", "datatype": "DYTS", "station": "GHCND:USC00241875", "attributes": " ", "value": 7}, {"date": "2004-01-01T00:00:00", "datatype": "EMNT", "station": "GHCND:USC00241875", "attributes": "0,0105, ", "value": -35}, {"date": "2004-01-01T00:00:00", "datatype": "EMXP", "station": "GHCND:USC00241875", "attributes": " ,0,0806, ", "value": 14}, {"date": "2004-01-01T00:00:00", "datatype": "EMXT", "station": "GHCND:USC00241875", "attributes": "0,0718, ", "value": 40}, {"date": "2004-01-01T00:00:00", "datatype": "FZF0", "station": "GHCND:USC00241875", "attributes": "0,0921", "value": -2.2}, {"date": "2004-01-01T00:00:00", "datatype": "FZF1", "station": "GHCND:USC00241875", "attributes": "0,0921", "value": -2.2}, {"date": "2004-01-01T00:00:00", "datatype": "FZF2", "station": "GHCND:USC00241875", "attributes": "0,1001", "value": -9.4}, {"date": "2004-01-01T00:00:00", "datatype": "FZF3", "station": "GHCND:USC00241875", "attributes": "0,1001", "value": -9.4}, {"date": "2004-01-01T00:00:00", "datatype": "FZF4", "station": "GHCND:USC00241875", "attributes": "0,1001", "value": -9.4}, {"date": "2004-01-01T00:00:00", "datatype": "FZF5", "station": "GHCND:USC00241875", "attributes": "0,0618", "value": -2.2}, {"date": "2004-01-01T00:00:00", "datatype": "FZF6", "station": "GHCND:USC00241875", "attributes": "0,0618", "value": -2.2}, {"date": "2004-01-01T00:00:00", "datatype": "FZF7", "station": "GHCND:USC00241875", "attributes": "0,0513", "value": -6.7}, {"date": "2004-01-01T00:00:00", "datatype": "FZF8", "station": "GHCND:USC00241875", "attributes": "0,0513", "value": -6.7}, {"date": "2004-01-01T00:00:00", "datatype": "FZF9", "station": "GHCND:USC00241875", "attributes": "0,0303", "value": -12.2}, {"date": "2004-01-01T00:00:00", "datatype": "PRCP", "station": "GHCND:USC00241875", "attributes": " ,0", "value": 200}, {"date": "2004-01-01T00:00:00", "datatype": "TAVG", "station": "GHCND:USC00241875", "attributes": "0", "value": 7.18}, {"date": "2004-01-01T00:00:00", "datatype": "TMAX", "station": "GHCND:USC00241875", "attributes": "0", "value": 14.84}, {"date": "2004-01-01T00:00:00", "datatype": "TMIN", "station": "GHCND:USC00241875", "attributes": "0", "value": -0.48}, {"date": "2005-01-01T00:00:00", "datatype": "DYFG", "station": "GHCND:USC00241875", "attributes": " ", "value": 1}, {"date": "2005-01-01T00:00:00", "datatype": "DYTS", "station": "GHCND:USC00241875", "attributes": " ", "value": 10}, {"date": "2006-01-01T00:00:00", "datatype": "DP01", "station": "GHCND:USC00241875", "attributes": "0", "value": 49}, {"date": "2006-01-01T00:00:00", "datatype": "DP10", "station": "GHCND:USC00241875", "attributes": "0", "value": 31}, {"date": "2006-01-01T00:00:00", "datatype": "DP1X", "station": "GHCND:USC00241875", "attributes": "0", "value": 1}, {"date": "2006-01-01T00:00:00", "datatype": "DSND", "station": "GHCND:USC00241875", "value": 10}, {"date": "2006-01-01T00:00:00", "datatype": "DSNW", "station": "GHCND:USC00241875", "attributes": "0", "value": 0}, {"date": "2006-01-01T00:00:00", "datatype": "DT00", "station": "GHCND:USC00241875", "attributes": "0", "value": 14}, {"date": "2006-01-01T00:00:00", "datatype": "DT32", "station": "GHCND:USC00241875", "attributes": "0", "value": 184}, {"date": "2006-01-01T00:00:00", "datatype": "DX32", "station": "GHCND:USC00241875", "attributes": "0", "value": 25}, {"date": "2006-01-01T00:00:00", "datatype": "DX70", "station": "GHCND:USC00241875", "attributes": "0", "value": 126}, {"date": "2006-01-01T00:00:00", "datatype": "DX90", "station": "GHCND:USC00241875", "attributes": "0", "value": 39}, {"date": "2006-01-01T00:00:00", "datatype": "DYFG", "station": "GHCND:USC00241875", "attributes": " ", "value": 3}, {"date": "2006-01-01T00:00:00", "datatype": "DYTS", "station": "GHCND:USC00241875", "attributes": " ", "value": 5}, {"date": "2006-01-01T00:00:00", "datatype": "EMNT", "station": "GHCND:USC00241875", "attributes": "0,0217, ", "value": -29.4}, {"date": "2006-01-01T00:00:00", "datatype": "EMSD", "station": "GHCND:USC00241875", "attributes": " ,0,0320, ", "value": 76}, {"date": "2006-01-01T00:00:00", "datatype": "EMSN", "station": "GHCND:USC00241875", "attributes": " ,0,1231,+", "value": 0}, {"date": "2006-01-01T00:00:00", "datatype": "EMXP", "station": "GHCND:USC00241875", "attributes": " ,0,0406, ", "value": 38.1}, {"date": "2006-01-01T00:00:00", "datatype": "EMXT", "station": "GHCND:USC00241875", "attributes": "0,0723,+", "value": 38.9}, {"date": "2006-01-01T00:00:00", "datatype": "FZF0", "station": "GHCND:USC00241875", "attributes": "0,0919", "value": -0.6}, {"date": "2006-01-01T00:00:00", "datatype": "FZF1", "station": "GHCND:USC00241875", "attributes": "0,1010", "value": -3.9}, {"date": "2006-01-01T00:00:00", "datatype": "FZF2", "station": "GHCND:USC00241875", "attributes": "0,1011", "value": -8.3}, {"date": "2006-01-01T00:00:00", "datatype": "FZF3", "station": "GHCND:USC00241875", "attributes": "0,1011", "value": -8.3}, {"date": "2006-01-01T00:00:00", "datatype": "FZF4", "station": "GHCND:USC00241875", "attributes": "0,1031", "value": -16.7}, {"date": "2006-01-01T00:00:00", "datatype": "FZF5", "station": "GHCND:USC00241875", "attributes": "0,0511", "value": -2.8}, {"date": "2006-01-01T00:00:00", "datatype": "FZF6", "station": "GHCND:USC00241875", "attributes": "0,0511", "value": -2.8}, {"date": "2006-01-01T00:00:00", "datatype": "FZF7", "station": "GHCND:USC00241875", "attributes": "0,0505", "value": -6.1}, {"date": "2006-01-01T00:00:00", "datatype": "FZF8", "station": "GHCND:USC00241875", "attributes": "0,0324", "value": -6.7}, {"date": "2006-01-01T00:00:00", "datatype": "FZF9", "station": "GHCND:USC00241875", "attributes": "0,0323", "value": -8.9}, {"date": "2006-01-01T00:00:00", "datatype": "PRCP", "station": "GHCND:USC00241875", "attributes": " ,0", "value": 235.8}, {"date": "2006-01-01T00:00:00", "datatype": "SNOW", "station": "GHCND:USC00241875", "attributes": " ,0", "value": 0}, {"date": "2006-01-01T00:00:00", "datatype": "TAVG", "station": "GHCND:USC00241875", "attributes": "0", "value": 8.52}, {"date": "2006-01-01T00:00:00", "datatype": "TMAX", "station": "GHCND:USC00241875", "attributes": "0", "value": 16.2}, {"date": "2006-01-01T00:00:00", "datatype": "TMIN", "station": "GHCND:USC00241875", "attributes": "0", "value": 0.83}, {"date": "2007-01-01T00:00:00", "datatype": "DP01", "station": "GHCND:USC00241875", "attributes": "0", "value": 51}, {"date": "2007-01-01T00:00:00", "datatype": "DP10", "station": "GHCND:USC00241875", "attributes": "0", "value": 32}, {"date": "2007-01-01T00:00:00", "datatype": "DP1X", "station": "GHCND:USC00241875", "attributes": "0", "value": 2}, {"date": "2007-01-01T00:00:00", "datatype": "DSND", "station": "GHCND:USC00241875", "value": 17}, {"date": "2007-01-01T00:00:00", "datatype": "DSNW", "station": "GHCND:USC00241875", "attributes": "0", "value": 0}, {"date": "2007-01-01T00:00:00", "datatype": "DT00", "station": "GHCND:USC00241875", "attributes": "0", "value": 20}, {"date": "2007-01-01T00:00:00", "datatype": "DT32", "station": "GHCND:USC00241875", "attributes": "0", "value": 160}, {"date": "2007-01-01T00:00:00", "datatype": "DX32", "station": "GHCND:USC00241875", "attributes": "0", "value": 49}, {"date": "2007-01-01T00:00:00", "datatype": "DX70", "station": "GHCND:USC00241875", "attributes": "0", "value": 131}, {"date": "2007-01-01T00:00:00", "datatype": "DX90", "station": "GHCND:USC00241875", "attributes": "0", "value": 41}, {"date": "2007-01-01T00:00:00", "datatype": "DYFG", "station": "GHCND:USC00241875", "attributes": " ", "value": 2}, {"date": "2007-01-01T00:00:00", "datatype": "DYTS", "station": "GHCND:USC00241875", "attributes": " ", "value": 12}, {"date": "2007-01-01T00:00:00", "datatype": "EMNT", "station": "GHCND:USC00241875", "attributes": "0,0215, ", "value": -30.6}, {"date": "2007-01-01T00:00:00", "datatype": "EMSD", "station": "GHCND:USC00241875", "attributes": " ,0,0215, ", "value": 203}, {"date": "2007-01-01T00:00:00", "datatype": "EMSN", "station": "GHCND:USC00241875", "attributes": " ,0,0329,+", "value": 10}, {"date": "2007-01-01T00:00:00", "datatype": "EMXP", "station": "GHCND:USC00241875", "attributes": " ,0,0523, ", "value": 27.9}, {"date": "2007-01-01T00:00:00", "datatype": "EMXT", "station": "GHCND:USC00241875", "attributes": "0,0724, ", "value": 41.7}, {"date": "2007-01-01T00:00:00", "datatype": "FZF0", "station": "GHCND:USC00241875", "attributes": "0,0909", "value": 0}, {"date": "2007-01-01T00:00:00", "datatype": "FZF1", "station": "GHCND:USC00241875", "attributes": "0,0914", "value": -6.1}, {"date": "2007-01-01T00:00:00", "datatype": "FZF2", "station": "GHCND:USC00241875", "attributes": "0,0914", "value": -6.1}, {"date": "2007-01-01T00:00:00", "datatype": "FZF3", "station": "GHCND:USC00241875", "attributes": "0,1027", "value": -9.4}, {"date": "2007-01-01T00:00:00", "datatype": "FZF4", "station": "GHCND:USC00241875", "attributes": "0,1027", "value": -9.4}, {"date": "2007-01-01T00:00:00", "datatype": "FZF5", "station": "GHCND:USC00241875", "attributes": "0,0526", "value": -1.1}, {"date": "2007-01-01T00:00:00", "datatype": "FZF6", "station": "GHCND:USC00241875", "attributes": "0,0413", "value": -6.1}, {"date": "2007-01-01T00:00:00", "datatype": "FZF7", "station": "GHCND:USC00241875", "attributes": "0,0413", "value": -6.1}, {"date": "2007-01-01T00:00:00", "datatype": "FZF8", "station": "GHCND:USC00241875", "attributes": "0,0408", "value": -8.9}, {"date": "2007-01-01T00:00:00", "datatype": "FZF9", "station": "GHCND:USC00241875", "attributes": "0,0408", "value": -8.9}, {"date": "2007-01-01T00:00:00", "datatype": "HDSD", "station": "GHCND:USC00241875", "attributes": "9", "value": 4040.9}, {"date": "2007-01-01T00:00:00", "datatype": "HTDD", "station": "GHCND:USC00241875", "attributes": "0", "value": 4040.9}, {"date": "2007-01-01T00:00:00", "datatype": "PRCP", "station": "GHCND:USC00241875", "attributes": " ,0", "value": 297.7}, {"date": "2007-01-01T00:00:00", "datatype": "SNOW", "station": "GHCND:USC00241875", "attributes": " ,0", "value": 61}, {"date": "2007-01-01T00:00:00", "datatype": "TAVG", "station": "GHCND:USC00241875", "attributes": "0", "value": 8.17}, {"date": "2007-01-01T00:00:00", "datatype": "TMAX", "station": "GHCND:USC00241875", "attributes": "0", "value": 15.51}, {"date": "2007-01-01T00:00:00", "datatype": "TMIN", "station": "GHCND:USC00241875", "attributes": "0", "value": 0.83}, {"date": "2008-01-01T00:00:00", "datatype": "CDSD", "station": "GHCND:USC00241875", "value": 216.5}, {"date": "2008-01-01T00:00:00", "datatype": "CLDD", "station": "GHCND:USC00241875", "attributes": "0", "value": 216.5}, {"date": "2008-01-01T00:00:00", "datatype": "DP01", "station": "GHCND:USC00241875", "attributes": "0", "value": 62}, {"date": "2008-01-01T00:00:00", "datatype": "DP10", "station": "GHCND:USC00241875", "attributes": "0", "value": 36}, {"date": "2008-01-01T00:00:00", "datatype": "DP1X", "station": "GHCND:USC00241875", "attributes": "0", "value": 2}, {"date": "2008-01-01T00:00:00", "datatype": "DSND", "station": "GHCND:USC00241875", "value": 60}, {"date": "2008-01-01T00:00:00", "datatype": "DSNW", "station": "GHCND:USC00241875", "attributes": "0", "value": 8}, {"date": "2008-01-01T00:00:00", "datatype": "DT00", "station": "GHCND:USC00241875", "attributes": "0", "value": 35}, {"date": "2008-01-01T00:00:00", "datatype": "DT32", "station": "GHCND:USC00241875", "attributes": "0", "value": 185}, {"date": "2008-01-01T00:00:00", "datatype": "DX32", "station": "GHCND:USC00241875", "attributes": "0", "value": 46}, {"date": "2008-01-01T00:00:00", "datatype": "DX70", "station": "GHCND:USC00241875", "attributes": "0", "value": 121}, {"date": "2008-01-01T00:00:00", "datatype": "DX90", "station": "GHCND:USC00241875", "attributes": "0", "value": 26}, {"date": "2008-01-01T00:00:00", "datatype": "DYTS", "station": "GHCND:USC00241875", "attributes": " ", "value": 7}, {"date": "2008-01-01T00:00:00", "datatype": "EMNT", "station": "GHCND:USC00241875", "attributes": "0,1215, ", "value": -35.6}, {"date": "2008-01-01T00:00:00", "datatype": "EMSD", "station": "GHCND:USC00241875", "attributes": " ,0,1227,+", "value": 152}, {"date": "2008-01-01T00:00:00", "datatype": "EMSN", "station": "GHCND:USC00241875", "attributes": " ,0,1213,+", "value": 117}, {"date": "2008-01-01T00:00:00", "datatype": "EMXP", "station": "GHCND:USC00241875", "attributes": " ,0,0617, ", "value": 35.6}, {"date": "2008-01-01T00:00:00", "datatype": "EMXT", "station": "GHCND:USC00241875", "attributes": "0,0825,+", "value": 38.9}, {"date": "2008-01-01T00:00:00", "datatype": "FZF0", "station": "GHCND:USC00241875", "attributes": "0,0908", "value": -3.3}, {"date": "2008-01-01T00:00:00", "datatype": "FZF1", "station": "GHCND:USC00241875", "attributes": "0,0908", "value": -3.3}, {"date": "2008-01-01T00:00:00", "datatype": "FZF2", "station": "GHCND:USC00241875", "attributes": "0,1009", "value": -5.6}, {"date": "2008-01-01T00:00:00", "datatype": "FZF3", "station": "GHCND:USC00241875", "attributes": "0,1027", "value": -10}, {"date": "2008-01-01T00:00:00", "datatype": "FZF4", "station": "GHCND:USC00241875", "attributes": "0,1027", "value": -10}, {"date": "2008-01-01T00:00:00", "datatype": "FZF5", "station": "GHCND:USC00241875", "attributes": "0,0503", "value": -3.3}, {"date": "2008-01-01T00:00:00", "datatype": "FZF6", "station": "GHCND:USC00241875", "attributes": "0,0503", "value": -3.3}, {"date": "2008-01-01T00:00:00", "datatype": "FZF7", "station": "GHCND:USC00241875", "attributes": "0,0427", "value": -6.1}, {"date": "2008-01-01T00:00:00", "datatype": "FZF8", "station": "GHCND:USC00241875", "attributes": "0,0423", "value": -8.3}, {"date": "2008-01-01T00:00:00", "datatype": "FZF9", "station": "GHCND:USC00241875", "attributes": "0,0421", "value": -11.7}, {"date": "2008-01-01T00:00:00", "datatype": "PRCP", "station": "GHCND:USC00241875", "attributes": " ,0", "value": 335.9}, {"date": "2008-01-01T00:00:00", "datatype": "SNOW", "station": "GHCND:USC00241875", "attributes": " ,0", "value": 496}, {"date": "2008-01-01T00:00:00", "datatype": "TAVG", "station": "GHCND:USC00241875", "attributes": "0", "value": 6.15}, {"date": "2008-01-01T00:00:00", "datatype": "TMAX", "station": "GHCND:USC00241875", "attributes": "0", "value": 13.9}, {"date": "2008-01-01T00:00:00", "datatype": "TMIN", "station": "GHCND:USC00241875", "attributes": "0", "value": -1.6}, {"date": "2009-01-01T00:00:00", "datatype": "CDSD", "station": "GHCND:USC00241875", "value": 178.7}, {"date": "2009-01-01T00:00:00", "datatype": "CLDD", "station": "GHCND:USC00241875", "attributes": "0", "value": 178.7}, {"date": "2009-01-01T00:00:00", "datatype": "DP01", "station": "GHCND:USC00241875", "attributes": "0", "value": 63}, {"date": "2009-01-01T00:00:00", "datatype": "DP10", "station": "GHCND:USC00241875", "attributes": "0", "value": 43}, {"date": "2009-01-01T00:00:00", "datatype": "DP1X", "station": "GHCND:USC00241875", "attributes": "0", "value": 1}, {"date": "2009-01-01T00:00:00", "datatype": "DSND", "station": "GHCND:USC00241875", "value": 43}, {"date": "2009-01-01T00:00:00", "datatype": "DSNW", "station": "GHCND:USC00241875", "attributes": "0", "value": 9}, {"date": "2009-01-01T00:00:00", "datatype": "DT00", "station": "GHCND:USC00241875", "attributes": "0", "value": 32}, {"date": "2009-01-01T00:00:00", "datatype": "DT32", "station": "GHCND:USC00241875", "attributes": "0", "value": 199}, {"date": "2009-01-01T00:00:00", "datatype": "DX32", "station": "GHCND:USC00241875", "attributes": "0", "value": 58}, {"date": "2009-01-01T00:00:00", "datatype": "DX70", "station": "GHCND:USC00241875", "attributes": "0", "value": 127}, {"date": "2009-01-01T00:00:00", "datatype": "DX90", "station": "GHCND:USC00241875", "attributes": "0", "value": 26}, {"date": "2009-01-01T00:00:00", "datatype": "DYFG", "station": "GHCND:USC00241875", "attributes": " ", "value": 9}, {"date": "2009-01-01T00:00:00", "datatype": "DYTS", "station": "GHCND:USC00241875", "attributes": " ", "value": 14}, {"date": "2009-01-01T00:00:00", "datatype": "EMNT", "station": "GHCND:USC00241875", "attributes": "0,1215, ", "value": -37.8}, {"date": "2009-01-01T00:00:00", "datatype": "EMSD", "station": "GHCND:USC00241875", "attributes": " ,0,1213,+", "value": 254}, {"date": "2009-01-01T00:00:00", "datatype": "EMSN", "station": "GHCND:USC00241875", "attributes": " ,0,1213,+", "value": 152}, {"date": "2009-01-01T00:00:00", "datatype": "EMXP", "station": "GHCND:USC00241875", "attributes": " ,0,0429, ", "value": 31}, {"date": "2009-01-01T00:00:00", "datatype": "EMXT", "station": "GHCND:USC00241875", "attributes": "0,0723,+", "value": 36.7}, {"date": "2009-01-01T00:00:00", "datatype": "FZF0", "station": "GHCND:USC00241875", "attributes": "0,0922", "value": -2.2}, {"date": "2009-01-01T00:00:00", "datatype": "FZF1", "station": "GHCND:USC00241875", "attributes": "0,0922", "value": -2.2}, {"date": "2009-01-01T00:00:00", "datatype": "FZF2", "station": "GHCND:USC00241875", "attributes": "0,0928", "value": -5.6}, {"date": "2009-01-01T00:00:00", "datatype": "FZF3", "station": "GHCND:USC00241875", "attributes": "0,1009", "value": -7.2}, {"date": "2009-01-01T00:00:00", "datatype": "FZF4", "station": "GHCND:USC00241875", "attributes": "0,1012", "value": -10}, {"date": "2009-01-01T00:00:00", "datatype": "FZF5", "station": "GHCND:USC00241875", "attributes": "0,0610", "value": -1.1}, {"date": "2009-01-01T00:00:00", "datatype": "FZF6", "station": "GHCND:USC00241875", "attributes": "0,0516", "value": -4.4}, {"date": "2009-01-01T00:00:00", "datatype": "FZF7", "station": "GHCND:USC00241875", "attributes": "0,0516", "value": -4.4}, {"date": "2009-01-01T00:00:00", "datatype": "FZF8", "station": "GHCND:USC00241875", "attributes": "0,0406", "value": -7.2}, {"date": "2009-01-01T00:00:00", "datatype": "FZF9", "station": "GHCND:USC00241875", "attributes": "0,0401", "value": -13.3}, {"date": "2009-01-01T00:00:00", "datatype": "HDSD", "station": "GHCND:USC00241875", "attributes": "2", "value": 4395.2}, {"date": "2009-01-01T00:00:00", "datatype": "HTDD", "station": "GHCND:USC00241875", "attributes": "0", "value": 4395.2}, {"date": "2009-01-01T00:00:00", "datatype": "PRCP", "station": "GHCND:USC00241875", "attributes": " ,0", "value": 324.5}, {"date": "2009-01-01T00:00:00", "datatype": "SNOW", "station": "GHCND:USC00241875", "attributes": " ,0", "value": 775}, {"date": "2009-01-01T00:00:00", "datatype": "TAVG", "station": "GHCND:USC00241875", "attributes": "0", "value": 6.05}, {"date": "2009-01-01T00:00:00", "datatype": "TMAX", "station": "GHCND:USC00241875", "attributes": "0", "value": 13.5}, {"date": "2009-01-01T00:00:00", "datatype": "TMIN", "station": "GHCND:USC00241875", "attributes": "0", "value": -1.39}]}